odoo9_addon_openeducat_achievement-9.0.2.4.0-py2.7-nspkg.pth
odoo9_addon_openeducat_achievement-9.0.2.4.0.dist-info/top_level.txt
odoo9_addon_openeducat_achievement-9.0.2.4.0.dist-info/WHEEL
odoo9_addon_openeducat_achievement-9.0.2.4.0.dist-info/RECORD
odoo9_addon_openeducat_achievement-9.0.2.4.0.dist-info/metadata.json
odoo9_addon_openeducat_achievement-9.0.2.4.0.dist-info/DESCRIPTION.rst
odoo9_addon_openeducat_achievement-9.0.2.4.0.dist-info/METADATA
odoo9_addon_openeducat_achievement-9.0.2.4.0.dist-info/namespace_packages.txt
odoo_addons/openeducat_achievement/achievement_menu.xml
odoo_addons/openeducat_achievement/__openerp__.py
odoo_addons/openeducat_achievement/__init__.py
odoo_addons/openeducat_achievement/security/ir.model.access.csv
odoo_addons/openeducat_achievement/models/achievement.py
odoo_addons/openeducat_achievement/models/__init__.py
odoo_addons/openeducat_achievement/models/achievement_type.py
odoo_addons/openeducat_achievement/i18n/openeducat_achievement.pot
odoo_addons/openeducat_achievement/views/achievement_view.xml
odoo_addons/openeducat_achievement/views/achievement_type_view.xml
odoo_addons/openeducat_achievement/demo/op.achievement.type.csv
odoo_addons/openeducat_achievement/demo/op.achievement.csv
odoo_addons/openeducat_achievement/static/description/openeducat_logo.png
odoo_addons/openeducat_achievement/static/description/achievement.png
odoo_addons/openeducat_achievement/static/description/index.html
odoo_addons/openeducat_achievement/static/description/openeducat_achievement_banner.jpg
odoo_addons/openeducat_achievement/static/description/icon.png
